<BatRecord>
	<Firmware>2.2.6</Firmware>
	<SN>1289</SN>
	<Filename>12890952.wav</Filename>
	<DateTime>03.06.2018 23:25:58</DateTime>
	<Duration>6 Sec</Duration>
	<Samplerate>312500 Hz</Samplerate>
	<Temperature>23 C</Temperature>
	<BattVoltage>3.6 V</BattVoltage>
	<GPS>
		<Valid>yes</Valid>
		<Position>51.615387 -3.973249</Position>
		<Altitude>86.067001 m</Altitude>
		<CH1903>-190183/777026</CH1903>
		<HDOP>1.320000</HDOP>
		<SatsUsed>7</SatsUsed>
		<GPSTimestamp>23:25:36+2h</GPSTimestamp>
		<GPSAge>0 Sec</GPSAge>
	</GPS>
	<Trigger>
		<TRIG_MODE>Crest Adv</TRIG_MODE>
		<Version>V1.0</Version>
		<Event>ManualTriggered</Event>
	</Trigger>
</BatRecord>
